{
  "version": "7",
  "dialect": "postgresql",
  "entries": [
    {
      "idx": 0,
      "version": "7",
      "when": 1780690115691,
      "tag": "0000_elite_dragon_man",
      "breakpoints": true
    },
    {
      "idx": 1,
      "version": "7",
      "when": 1780700468231,
      "tag": "0001_romantic_leopardon",
      "breakpoints": true
    },
    {
      "idx": 2,
      "version": "7",
      "when": 1780700680554,
      "tag": "0002_boring_pestilence",
      "breakpoints": true
    },
    {
      "idx": 3,
      "version": "7",
      "when": 1780700824292,
      "tag": "0003_glamorous_dormammu",
      "breakpoints": true
    }
  ]
}
